django_changelist_inline/__init__.py
django_changelist_inline/admin.py
django_changelist_inline/apps.py
django_changelist_inline/static/django_changelist_inline/css/changelist_inline.css
django_changelist_inline/templates/django_changelist_inline/changelist_inline.html
django_changelist_inline-1.0.3.dist-info/LICENSE
django_changelist_inline-1.0.3.dist-info/METADATA
django_changelist_inline-1.0.3.dist-info/WHEEL
django_changelist_inline-1.0.3.dist-info/top_level.txt
django_changelist_inline-1.0.3.dist-info/RECORD
