Metadata-Version: 2.1
Name: django-changelist-inline
Version: 1.0.3
Summary: Inline Changelists for Django
Home-page: https://git.bthlabs.pl/tomekwojcik/django-changelist-inline
Author: Tomek Wójcik
Author-email: contact@bthlabs.pl
Maintainer: BTHLabs
Maintainer-email: contact@bthlabs.pl
License: Other/Proprietary License
Platform: any
Classifier: License :: OSI Approved :: MIT License
Requires-Python: >=3.8
Requires-Dist: Django (>=2.2)
Provides-Extra: dev
Requires-Dist: factory-boy (==2.12.0) ; extra == 'dev'
Requires-Dist: flake8-commas (==2.0.0) ; extra == 'dev'
Requires-Dist: flake8 (==3.8.3) ; extra == 'dev'
Requires-Dist: pytest-django (==4.2.0) ; extra == 'dev'
Requires-Dist: pytest (==6.2.3) ; extra == 'dev'
Requires-Dist: twine (==2.0.0) ; extra == 'dev'
